{
  "AuthConfigProperties": [
    {
      "AIChatbotPopoverTitle": {
        "EnabledForFlyout": false,
        "HelperUI": null,
        "Hidden": false,
        "PropertyGroupName": "",
        "PropertyKind": 1,
        "SectionIndex": 0,
        "SectionName": "data",
        "SectionType": null,
        "ShowInCanvasInlineActionBar": false,
        "Type": 0,
        "WizardStep": null
      },
      "ButtonText": {
        "EnabledForFlyout": false,
        "HelperUI": null,
        "Hidden": false,
        "PropertyGroupName": "",
        "PropertyKind": 1,
        "SectionIndex": 0,
        "SectionName": "data",
        "SectionType": null,
        "ShowInCanvasInlineActionBar": false,
        "Type": 0,
        "WizardStep": null
      },
      "Definition": {
        "EnabledForFlyout": false,
        "HelperUI": null,
        "Hidden": false,
        "PropertyGroupName": "",
        "PropertyKind": 1,
        "SectionIndex": 0,
        "SectionName": "data",
        "SectionType": null,
        "ShowInCanvasInlineActionBar": false,
        "Type": 0,
        "WizardStep": null
      },
      "Disclaimer": {
        "EnabledForFlyout": false,
        "HelperUI": null,
        "Hidden": false,
        "PropertyGroupName": "",
        "PropertyKind": 1,
        "SectionIndex": 0,
        "SectionName": "data",
        "SectionType": null,
        "ShowInCanvasInlineActionBar": false,
        "Type": 0,
        "WizardStep": null
      },
      "DisplayMode": {
        "EnabledForFlyout": false,
        "HelperUI": null,
        "Hidden": false,
        "PropertyGroupName": "",
        "PropertyKind": 1,
        "SectionIndex": 1,
        "SectionName": "design",
        "SectionType": null,
        "ShowInCanvasInlineActionBar": false,
        "Type": 27,
        "WizardStep": null
      },
      "Height": {
        "EnabledForFlyout": false,
        "HelperUI": null,
        "Hidden": false,
        "PropertyGroupName": "Size",
        "PropertyKind": 2,
        "SectionIndex": 1,
        "SectionName": "design",
        "SectionType": null,
        "ShowInCanvasInlineActionBar": false,
        "Type": 0,
        "WizardStep": null
      },
      "InputEvent": {
        "EnabledForFlyout": false,
        "HelperUI": null,
        "Hidden": false,
        "PropertyGroupName": "",
        "PropertyKind": 1,
        "SectionIndex": 0,
        "SectionName": "data",
        "SectionType": null,
        "ShowInCanvasInlineActionBar": false,
        "Type": 0,
        "WizardStep": null
      },
      "ShowDisclaimer": {
        "EnabledForFlyout": false,
        "HelperUI": null,
        "Hidden": false,
        "PropertyGroupName": "",
        "PropertyKind": 1,
        "SectionIndex": 0,
        "SectionName": "data",
        "SectionType": null,
        "ShowInCanvasInlineActionBar": false,
        "Type": 0,
        "WizardStep": null
      },
      "Visible": {
        "EnabledForFlyout": false,
        "HelperUI": null,
        "Hidden": false,
        "PropertyGroupName": "",
        "PropertyKind": 1,
        "SectionIndex": 1,
        "SectionName": "design",
        "SectionType": null,
        "ShowInCanvasInlineActionBar": false,
        "Type": 0,
        "WizardStep": null
      },
      "Width": {
        "EnabledForFlyout": false,
        "HelperUI": null,
        "Hidden": false,
        "PropertyGroupName": "Size",
        "PropertyKind": 2,
        "SectionIndex": 1,
        "SectionName": "design",
        "SectionType": null,
        "ShowInCanvasInlineActionBar": false,
        "Type": 0,
        "WizardStep": null
      },
      "X": {
        "EnabledForFlyout": false,
        "HelperUI": null,
        "Hidden": false,
        "PropertyGroupName": "Position",
        "PropertyKind": 2,
        "SectionIndex": 1,
        "SectionName": "design",
        "SectionType": null,
        "ShowInCanvasInlineActionBar": false,
        "Type": 0,
        "WizardStep": null
      },
      "Y": {
        "EnabledForFlyout": false,
        "HelperUI": null,
        "Hidden": false,
        "PropertyGroupName": "Position",
        "PropertyKind": 2,
        "SectionIndex": 1,
        "SectionName": "design",
        "SectionType": null,
        "ShowInCanvasInlineActionBar": false,
        "Type": 0,
        "WizardStep": null
      }
    }
  ],
  "CommonEvents": [
    {
      "Description": "",
      "DisplayName": "OnChange",
      "Hidden": false,
      "IsPrimaryInput": false,
      "Name": "OnChange",
      "PfxDefaultValue": null
    }
  ],
  "ControlConstructor": "AITeachingPopover",
  "ControlNamespace": "PowerCAT",
  "DisplayNameKey": "AITeachingPopover_Disp_Key",
  "Events": [
    {
      "Description": "OnSubmit",
      "DisplayName": "OnSubmit",
      "Hidden": false,
      "IsPrimaryInput": false,
      "Name": "OnSubmit",
      "PfxDefaultValue": null
    }
  ],
  "IncludedProperties": [
    {
      "Category": "design",
      "DefaultValue": "",
      "Description": "",
      "DescriptionResourceString": "",
      "DisplayName": "CC_X",
      "DisplayNameResourceString": "CC_X",
      "HelperUI": "",
      "Hidden": false,
      "IsDataSourceProperty": false,
      "IsLinkableToParentTheme": false,
      "IsPrimaryBehavioral": false,
      "IsPrimaryInput": false,
      "IsPrimaryOutput": false,
      "IsResettable": false,
      "IsResettableToManifestDefault": false,
      "Name": "X",
      "NullDefaultValue": "",
      "ParentDataSetName": "",
      "PassThroughProperty": "",
      "PfxDefaultValue": null,
      "PhoneDefaultValue": "",
      "Required": false,
      "ShouldAutoBind": false,
      "Type": 2,
      "Usage": 2,
      "WebDefaultValue": ""
    },
    {
      "Category": "design",
      "DefaultValue": "",
      "Description": "",
      "DescriptionResourceString": "",
      "DisplayName": "CC_Y",
      "DisplayNameResourceString": "CC_Y",
      "HelperUI": "",
      "Hidden": false,
      "IsDataSourceProperty": false,
      "IsLinkableToParentTheme": false,
      "IsPrimaryBehavioral": false,
      "IsPrimaryInput": false,
      "IsPrimaryOutput": false,
      "IsResettable": false,
      "IsResettableToManifestDefault": false,
      "Name": "Y",
      "NullDefaultValue": "",
      "ParentDataSetName": "",
      "PassThroughProperty": "",
      "PfxDefaultValue": null,
      "PhoneDefaultValue": "",
      "Required": false,
      "ShouldAutoBind": false,
      "Type": 2,
      "Usage": 2,
      "WebDefaultValue": ""
    },
    {
      "Category": "design",
      "DefaultValue": "200",
      "Description": "",
      "DescriptionResourceString": "",
      "DisplayName": "Width",
      "DisplayNameResourceString": "Width",
      "HelperUI": "",
      "Hidden": false,
      "IsDataSourceProperty": false,
      "IsLinkableToParentTheme": false,
      "IsPrimaryBehavioral": false,
      "IsPrimaryInput": false,
      "IsPrimaryOutput": false,
      "IsResettable": false,
      "IsResettableToManifestDefault": false,
      "Name": "Width",
      "NullDefaultValue": "0",
      "ParentDataSetName": "",
      "PassThroughProperty": "",
      "PfxDefaultValue": null,
      "PhoneDefaultValue": "350",
      "Required": false,
      "ShouldAutoBind": false,
      "Type": 2,
      "Usage": 2,
      "WebDefaultValue": "112"
    },
    {
      "Category": "design",
      "DefaultValue": "200",
      "Description": "",
      "DescriptionResourceString": "",
      "DisplayName": "Height",
      "DisplayNameResourceString": "Height",
      "HelperUI": "",
      "Hidden": false,
      "IsDataSourceProperty": false,
      "IsLinkableToParentTheme": false,
      "IsPrimaryBehavioral": false,
      "IsPrimaryInput": false,
      "IsPrimaryOutput": false,
      "IsResettable": false,
      "IsResettableToManifestDefault": false,
      "Name": "Height",
      "NullDefaultValue": "0",
      "ParentDataSetName": "",
      "PassThroughProperty": "",
      "PfxDefaultValue": null,
      "PhoneDefaultValue": "350",
      "Required": false,
      "ShouldAutoBind": false,
      "Type": 2,
      "Usage": 2,
      "WebDefaultValue": "112"
    },
    {
      "Category": "design",
      "DefaultValue": "true",
      "Description": "",
      "DescriptionResourceString": "",
      "DisplayName": "Visible",
      "DisplayNameResourceString": "Visible",
      "HelperUI": "",
      "Hidden": false,
      "IsDataSourceProperty": false,
      "IsLinkableToParentTheme": false,
      "IsPrimaryBehavioral": false,
      "IsPrimaryInput": false,
      "IsPrimaryOutput": false,
      "IsResettable": false,
      "IsResettableToManifestDefault": false,
      "Name": "Visible",
      "NullDefaultValue": "",
      "ParentDataSetName": "",
      "PassThroughProperty": "",
      "PfxDefaultValue": null,
      "PhoneDefaultValue": "",
      "Required": false,
      "ShouldAutoBind": false,
      "Type": 4,
      "Usage": 2,
      "WebDefaultValue": ""
    },
    {
      "Category": "design",
      "DefaultValue": "",
      "Description": "",
      "DescriptionResourceString": "",
      "DisplayName": "DisplayMode",
      "DisplayNameResourceString": "DisplayMode",
      "HelperUI": "",
      "Hidden": false,
      "IsDataSourceProperty": false,
      "IsLinkableToParentTheme": false,
      "IsPrimaryBehavioral": false,
      "IsPrimaryInput": false,
      "IsPrimaryOutput": false,
      "IsResettable": false,
      "IsResettableToManifestDefault": false,
      "Name": "DisplayMode",
      "NullDefaultValue": "",
      "ParentDataSetName": "",
      "PassThroughProperty": "",
      "PfxDefaultValue": null,
      "PhoneDefaultValue": "",
      "Required": false,
      "ShouldAutoBind": false,
      "Type": 27,
      "Usage": 2,
      "WebDefaultValue": ""
    }
  ],
  "Name": "AI Teaching popover",
  "Properties": [
    {
      "Category": "data",
      "DefaultValue": "AI Chatbot popover",
      "Description": "AITeachingPopover_Title_Desc_Key",
      "DescriptionResourceString": "AITeachingPopover_Title_Desc_Key",
      "DisplayName": "Title",
      "DisplayNameResourceString": "AITeachingPopover_Title_Disp_Key",
      "EnumValues": [],
      "HelperUI": "",
      "Hidden": false,
      "IsDataSourceProperty": false,
      "IsLinkableToParentTheme": false,
      "IsPrimaryBehavioral": false,
      "IsPrimaryInput": false,
      "IsPrimaryOutput": false,
      "IsResettable": false,
      "IsResettableToManifestDefault": false,
      "Name": "AIChatbotPopoverTitle",
      "ParentDataSetName": "",
      "PassThroughProperty": "",
      "PfxDefaultValue": "",
      "PhoneDefaultValue": "",
      "Required": false,
      "ShouldAutoBind": false,
      "Type": 6,
      "Usage": 2,
      "WebDefaultValue": ""
    },
    {
      "Category": "data",
      "DefaultValue": "Teaching popover",
      "Description": "Text to appear on the button",
      "DescriptionResourceString": "AITeachingPopover_ButtonText_Desc_Key",
      "DisplayName": "Button text",
      "DisplayNameResourceString": "AITeachingPopover_ButtonText_Disp_Key",
      "EnumValues": [],
      "HelperUI": "",
      "Hidden": false,
      "IsDataSourceProperty": false,
      "IsLinkableToParentTheme": false,
      "IsPrimaryBehavioral": false,
      "IsPrimaryInput": false,
      "IsPrimaryOutput": false,
      "IsResettable": false,
      "IsResettableToManifestDefault": false,
      "Name": "ButtonText",
      "ParentDataSetName": "",
      "PassThroughProperty": "",
      "PfxDefaultValue": "",
      "PhoneDefaultValue": "",
      "Required": false,
      "ShouldAutoBind": false,
      "Type": 6,
      "Usage": 0,
      "WebDefaultValue": ""
    },
    {
      "Category": "data",
      "DefaultValue": "AI-generated content may be incorrect",
      "Description": "AITeachingPopover_Disclaimer_Desc_Key",
      "DescriptionResourceString": "AITeachingPopover_Disclaimer_Desc_Key",
      "DisplayName": "Disclaimer",
      "DisplayNameResourceString": "AITeachingPopover_Disclaimer_Disp_Key",
      "EnumValues": [],
      "HelperUI": "",
      "Hidden": false,
      "IsDataSourceProperty": false,
      "IsLinkableToParentTheme": false,
      "IsPrimaryBehavioral": false,
      "IsPrimaryInput": false,
      "IsPrimaryOutput": false,
      "IsResettable": false,
      "IsResettableToManifestDefault": false,
      "Name": "Disclaimer",
      "ParentDataSetName": "",
      "PassThroughProperty": "",
      "PfxDefaultValue": "",
      "PhoneDefaultValue": "",
      "Required": false,
      "ShouldAutoBind": false,
      "Type": 6,
      "Usage": 0,
      "WebDefaultValue": ""
    },
    {
      "Category": "data",
      "DefaultValue": "",
      "Description": "Event which denotes the popover to show",
      "DescriptionResourceString": "AITeachingPopover_InputEvent_Desc_Key",
      "DisplayName": "Input event",
      "DisplayNameResourceString": "AITeachingPopover_InputEvent_Disp_Key",
      "EnumValues": [],
      "HelperUI": "",
      "Hidden": false,
      "IsDataSourceProperty": false,
      "IsLinkableToParentTheme": false,
      "IsPrimaryBehavioral": false,
      "IsPrimaryInput": false,
      "IsPrimaryOutput": false,
      "IsResettable": false,
      "IsResettableToManifestDefault": false,
      "Name": "InputEvent",
      "ParentDataSetName": "",
      "PassThroughProperty": "",
      "PfxDefaultValue": "",
      "PhoneDefaultValue": "",
      "Required": false,
      "ShouldAutoBind": false,
      "Type": 6,
      "Usage": 0,
      "WebDefaultValue": ""
    },
    {
      "Category": "data",
      "DefaultValue": "false",
      "Description": "Definition that is generator by custom AI Prompts",
      "DescriptionResourceString": "AITeachingPopover_Definition_Desc_Key",
      "DisplayName": "Definition",
      "DisplayNameResourceString": "AITeachingPopover_Definition_Disp_Key",
      "EnumValues": [],
      "HelperUI": "",
      "Hidden": false,
      "IsDataSourceProperty": false,
      "IsLinkableToParentTheme": false,
      "IsPrimaryBehavioral": false,
      "IsPrimaryInput": false,
      "IsPrimaryOutput": false,
      "IsResettable": false,
      "IsResettableToManifestDefault": false,
      "Name": "Definition",
      "ParentDataSetName": "",
      "PassThroughProperty": "",
      "PfxDefaultValue": "",
      "PhoneDefaultValue": "",
      "Required": false,
      "ShouldAutoBind": false,
      "Type": 6,
      "Usage": 0,
      "WebDefaultValue": ""
    },
    {
      "Category": "data",
      "DefaultValue": "true",
      "Description": "Show Disclaimer",
      "DescriptionResourceString": "AITeachingPopover_ShowDisclaimer_Disp_Key",
      "DisplayName": "Show Disclaimer",
      "DisplayNameResourceString": "AITeachingPopover_ShowDisclaimer_Disp_Key",
      "EnumValues": [],
      "HelperUI": "",
      "Hidden": false,
      "IsDataSourceProperty": false,
      "IsLinkableToParentTheme": false,
      "IsPrimaryBehavioral": false,
      "IsPrimaryInput": false,
      "IsPrimaryOutput": false,
      "IsResettable": false,
      "IsResettableToManifestDefault": false,
      "Name": "ShowDisclaimer",
      "ParentDataSetName": "",
      "PassThroughProperty": "",
      "PfxDefaultValue": "",
      "PhoneDefaultValue": "",
      "Required": false,
      "ShouldAutoBind": false,
      "Type": 20,
      "Usage": 0,
      "WebDefaultValue": ""
    },
    {
      "Category": "design",
      "DefaultValue": "",
      "Description": "NA",
      "DescriptionResourceString": "NA",
      "DisplayName": "NA",
      "DisplayNameResourceString": "NA",
      "EnumValues": [],
      "HelperUI": "",
      "Hidden": true,
      "IsDataSourceProperty": false,
      "IsLinkableToParentTheme": false,
      "IsPrimaryBehavioral": false,
      "IsPrimaryInput": false,
      "IsPrimaryOutput": false,
      "IsResettable": false,
      "IsResettableToManifestDefault": false,
      "Name": "TabIndex",
      "ParentDataSetName": "",
      "PassThroughProperty": "",
      "PfxDefaultValue": "",
      "PhoneDefaultValue": "",
      "Required": false,
      "ShouldAutoBind": false,
      "Type": 16,
      "Usage": 0,
      "WebDefaultValue": ""
    },
    {
      "Category": "design",
      "DefaultValue": "",
      "Description": "NA",
      "DescriptionResourceString": "NA",
      "DisplayName": "NA",
      "DisplayNameResourceString": "NA",
      "EnumValues": [],
      "HelperUI": "",
      "Hidden": true,
      "IsDataSourceProperty": false,
      "IsLinkableToParentTheme": false,
      "IsPrimaryBehavioral": false,
      "IsPrimaryInput": false,
      "IsPrimaryOutput": false,
      "IsResettable": false,
      "IsResettableToManifestDefault": false,
      "Name": "Tooltip",
      "ParentDataSetName": "",
      "PassThroughProperty": "",
      "PfxDefaultValue": "",
      "PhoneDefaultValue": "",
      "Required": false,
      "ShouldAutoBind": false,
      "Type": 6,
      "Usage": 0,
      "WebDefaultValue": ""
    },
    {
      "Category": "design",
      "DefaultValue": "",
      "Description": "",
      "DescriptionResourceString": "",
      "DisplayName": "PCFTeamsTheme",
      "DisplayNameResourceString": "",
      "HelperUI": "",
      "Hidden": true,
      "IsDataSourceProperty": false,
      "IsLinkableToParentTheme": false,
      "IsPrimaryBehavioral": false,
      "IsPrimaryInput": false,
      "IsPrimaryOutput": false,
      "IsResettable": false,
      "IsResettableToManifestDefault": false,
      "Name": "PCFTeamsTheme",
      "NullDefaultValue": "",
      "ParentDataSetName": "",
      "PassThroughProperty": "",
      "PfxDefaultValue": "",
      "PhoneDefaultValue": "",
      "Required": false,
      "ShouldAutoBind": false,
      "Type": 3,
      "Usage": 0,
      "WebDefaultValue": ""
    }
  ],
  "Resources": [
    {
      "IsControlSpecific": false,
      "LoadingOrder": 1,
      "ModifiedPath": "",
      "Path": "/PCF/prop-types.js",
      "Type": 0
    },
    {
      "IsControlSpecific": false,
      "LoadingOrder": 2,
      "ModifiedPath": "",
      "Path": "/PCF/react-fela.js",
      "Type": 0
    },
    {
      "IsControlSpecific": false,
      "LoadingOrder": 3,
      "ModifiedPath": "",
      "Path": "/PCF/fela.js",
      "Type": 0
    },
    {
      "IsControlSpecific": false,
      "LoadingOrder": 4,
      "ModifiedPath": "",
      "Path": "/PCF/fela-dom.js",
      "Type": 0
    },
    {
      "IsControlSpecific": false,
      "LoadingOrder": 5,
      "ModifiedPath": "",
      "Path": "/ctrllib/common/js/container.js",
      "Type": 0
    },
    {
      "IsControlSpecific": false,
      "LoadingOrder": 6,
      "ModifiedPath": "",
      "Path": "/ctrllib/PCFControls/js/PCFControlWrapper.js",
      "Type": 0
    },
    {
      "IsControlSpecific": false,
      "LoadingOrder": 7,
      "ModifiedPath": "",
      "Path": "/ctrllib/PcfControlProxy/js/PcfControlProxy.js",
      "Type": 0
    },
    {
      "IsControlSpecific": false,
      "LoadingOrder": 8,
      "ModifiedPath": "",
      "Path": "{\"Id\":\"ManifestTemplate\",\"Data\":{\"ConstructorName\":\"PowerCAT.AITeachingPopover\",\"CustomControlId\":\"PowerCAT.AITeachingPopover\",\"IsVirtual\":false,\"Properties\":{\"Resources\":[{\"Name\":\"/PCF/prop-types.js\",\"LoadOrder\":1,\"Type\":0,\"LibraryName\":null},{\"Name\":\"/PCF/react-fela.js\",\"LoadOrder\":2,\"Type\":0,\"LibraryName\":null},{\"Name\":\"/PCF/fela.js\",\"LoadOrder\":3,\"Type\":0,\"LibraryName\":null},{\"Name\":\"/PCF/fela-dom.js\",\"LoadOrder\":4,\"Type\":0,\"LibraryName\":null},{\"Name\":\"/ctrllib/common/js/container.js\",\"LoadOrder\":5,\"Type\":0,\"LibraryName\":null},{\"Name\":\"/ctrllib/PCFControls/js/PCFControlWrapper.js\",\"LoadOrder\":6,\"Type\":0,\"LibraryName\":null},{\"Name\":\"/ctrllib/PcfControlProxy/js/PcfControlProxy.js\",\"LoadOrder\":7,\"Type\":0,\"LibraryName\":null}],\"GroupDefinitions\":null,\"DataSetDefinitions\":{},\"Properties\":{\"AIChatbotPopoverTitle\":{\"Required\":true,\"Usage\":0,\"DefaultValue\":\"AI Chatbot popover\"},\"ButtonText\":{\"Required\":true,\"Usage\":1,\"DefaultValue\":\"Teaching popover\"},\"Disclaimer\":{\"Required\":true,\"Usage\":1,\"DefaultValue\":\"AI-generated content may be incorrect\"},\"InputEvent\":{\"Required\":true,\"Usage\":1,\"DefaultValue\":\"\"},\"Definition\":{\"Required\":true,\"Usage\":1,\"DefaultValue\":\"false\"},\"ShowDisclaimer\":{\"Required\":true,\"Usage\":1,\"DefaultValue\":\"true\"},\"TabIndex\":{\"Required\":true,\"Usage\":1,\"DefaultValue\":\"\"},\"Tooltip\":{\"Required\":true,\"Usage\":1,\"DefaultValue\":\"\"}},\"FeatureUsage\":null},\"Events\":{\"OnSubmit\":{\"EventName\":\"OnSubmit\"}},\"CommonEvents\":null,\"DesignMap\":null,\"PropertyDependencies\":[],\"Children\":null}}",
      "Type": 3
    },
    {
      "IsControlSpecific": false,
      "LoadingOrder": 9,
      "ModifiedPath": "",
      "Path": "{\"Id\":\"ManifestPropertyTypes\",\"Data\":{\"Properties\":[{\"Name\":\"AIChatbotPopoverTitle\",\"Type\":\"SingleLine_Text\",\"ComplexType\":\"None\",\"IsPrimary\":false,\"IsIncluded\":false},{\"Name\":\"ButtonText\",\"Type\":\"SingleLine_Text\",\"ComplexType\":\"None\",\"IsPrimary\":false,\"IsIncluded\":false},{\"Name\":\"Disclaimer\",\"Type\":\"SingleLine_Text\",\"ComplexType\":\"None\",\"IsPrimary\":false,\"IsIncluded\":false},{\"Name\":\"InputEvent\",\"Type\":\"SingleLine_Text\",\"ComplexType\":\"None\",\"IsPrimary\":false,\"IsIncluded\":false},{\"Name\":\"Definition\",\"Type\":\"SingleLine_Text\",\"ComplexType\":\"None\",\"IsPrimary\":false,\"IsIncluded\":false},{\"Name\":\"ShowDisclaimer\",\"Type\":\"TwoOptions\",\"ComplexType\":\"None\",\"IsPrimary\":false,\"IsIncluded\":false},{\"Name\":\"TabIndex\",\"Type\":\"Whole_None\",\"ComplexType\":\"\",\"IsPrimary\":false,\"IsIncluded\":false},{\"Name\":\"Tooltip\",\"Type\":\"SingleLine_Text\",\"ComplexType\":\"\",\"IsPrimary\":false,\"IsIncluded\":false},{\"Name\":\"PCFTeamsTheme\",\"Type\":\"String\",\"ComplexType\":\"\",\"IsPrimary\":false,\"IsIncluded\":true},{\"Name\":\"X\",\"Type\":\"Number\",\"ComplexType\":\"\",\"IsPrimary\":false,\"IsIncluded\":true},{\"Name\":\"Y\",\"Type\":\"Number\",\"ComplexType\":\"\",\"IsPrimary\":false,\"IsIncluded\":true},{\"Name\":\"Width\",\"Type\":\"Number\",\"ComplexType\":\"\",\"IsPrimary\":false,\"IsIncluded\":true},{\"Name\":\"Height\",\"Type\":\"Number\",\"ComplexType\":\"\",\"IsPrimary\":false,\"IsIncluded\":true},{\"Name\":\"Visible\",\"Type\":\"Boolean\",\"ComplexType\":\"\",\"IsPrimary\":false,\"IsIncluded\":true},{\"Name\":\"DisplayMode\",\"Type\":\"DisplayMode\",\"ComplexType\":\"\",\"IsPrimary\":false,\"IsIncluded\":true}]}}",
      "Type": 3
    },
    {
      "IsControlSpecific": false,
      "LoadingOrder": 10,
      "ModifiedPath": "",
      "Path": "{\"Id\":\"PowerAppsControlInfo\",\"Data\":{\"TemplateVersion\":1,\"Version\":\"0.0.42\",\"IsFirstParty\":false}}",
      "Type": 3
    },
    {
      "IsControlSpecific": true,
      "LoadingOrder": 11,
      "ModifiedPath": "https://docserverpwaprodwus.blob.core.windows.net/d208bc04-9b74-4163-9b80-9ec957fcdbe0-1/appdynamicresources/D%253a0SvcFab0_App0PowerApps.WebAuthoringType_App980work0a1lfnujj.trq020S0Resources0Controls0PowerCAT.AITeachingPopover.bundle.js?skoid=58690ece-ec83-4ce2-9ce8-883d4d6a54ee&sktid=975f013f-7f24-47e8-a7d3-abc4752bf346&skt=2024-03-31T06%3A22%3A03Z&ske=2024-04-01T06%3A37%3A03Z&sks=b&skv=2022-11-02&sv=2022-11-02&spr=https&se=2024-04-01T06%3A37%3A03Z&sr=b&sp=r&sig=QIVp65RAsFKIPpKUH2dybx04kbfnYyBMNiDR8a644TU%3D",
      "Path": "/PCFControls/cat_PowerCAT.AITeachingPopover/PowerCAT.AITeachingPopover.bundle.js",
      "Type": 0
    },
    {
      "IsControlSpecific": true,
      "LoadingOrder": 10,
      "ModifiedPath": "",
      "Path": "/PCFControls/cat_PowerCAT.AITeachingPopover/strings/PowerCAT.AITeachingPopover.AITeachingPopover.1033.resx",
      "Type": 2
    },
    {
      "IsControlSpecific": true,
      "LoadingOrder": 13,
      "ModifiedPath": "https://docserverpwaprodwus.blob.core.windows.net/d208bc04-9b74-4163-9b80-9ec957fcdbe0-1/appdynamicresources/D%253a0SvcFab0_App0PowerApps.WebAuthoringType_App980work0a1lfnujj.trq020S0Resources0Controls0strings%252fPowerCAT.AITeachingPopover.AITeachingPopover.1033.json?skoid=58690ece-ec83-4ce2-9ce8-883d4d6a54ee&sktid=975f013f-7f24-47e8-a7d3-abc4752bf346&skt=2024-03-31T06%3A22%3A03Z&ske=2024-04-01T06%3A37%3A03Z&sks=b&skv=2022-11-02&sv=2022-11-02&spr=https&se=2024-04-01T06%3A37%3A03Z&sr=b&sp=r&sig=nDStI%2BzEKD24%2FEkRQBfYmp%2FQGz%2Fp1OZDG8%2BEHlZRiYk%3D",
      "Path": "/PCFControls/cat_PowerCAT.AITeachingPopover/strings/PowerCAT.AITeachingPopover.AITeachingPopover.1033.json",
      "Type": 5
    },
    {
      "IsControlSpecific": false,
      "LoadingOrder": 13,
      "ModifiedPath": "",
      "Path": "{\"Id\":\"LocalizedStrings\",\"Data\":{\"LocStrings\":{\"AITeachingPopover_Disp_Key\":\"AI Teaching popover\",\"AITeachingPopover_Title_Disp_Key\":\"Title\",\"AITeachingPopover_AccessibleLabel_Disp_Key\":\"Accessible Label\",\"AITeachingPopover_Disclaimer_Disp_Key\":\"Disclaimer\",\"AITeachingPopover_ShowDisclaimer_Disp_Key\":\"Show Disclaimer\",\"AITeachingPopover_Definition_Disp_Key\":\"Definition\",\"AITeachingPopover_ButtonText_Disp_Key\":\"Button text\",\"AITeachingPopover_ButtonText_Desc_Key\":\"Text to appear on the button\",\"AITeachingPopover_Definition_Desc_Key\":\"Definition that is generator by custom AI Prompts\",\"AITeachingPopover_InputEvent_Disp_Key\":\"Input event\",\"AITeachingPopover_InputEvent_Desc_Key\":\"Event which denotes the popover to show\"}}}",
      "Type": 3
    },
    {
      "IsControlSpecific": false,
      "LoadingOrder": 5,
      "ModifiedPath": "",
      "Path": "/PCF/fluentui-react.js",
      "Type": 0
    }
  ],
  "Version": "0.0.42"
}