{
  "ComponentAllowCustomization": true,
  "ComponentChangedSinceFileImport": true,
  "ComponentManifest": {
    "AllowAccessToGlobals": true,
    "AllowCustomization": true,
    "Description": "",
    "Name": "CommandBarOverflowItems",
    "TemplateGuid": "ee65712cedf944b38accbde33a5ae71c"
  },
  "ComponentType": "CanvasComponent",
  "CustomGroupControlTemplateName": "",
  "CustomProperties": [
    {
      "Category": 0,
      "DisplayName": "Component Height",
      "Hidden": true,
      "Name": "ComponentHeight",
      "PropertyDataTypeKey": "Number",
      "Tooltip": "Component Height",
      "Type": "{\"Version\":\"1.324\",\"Type\":{\"Name\":\"Root\",\"Kind\":\"Number\",\"EnumString\":\"\",\"Type\":[]}}"
    }
  ],
  "FirstParty": true,
  "Id": "http://microsoft.com/appmagic/Component",
  "IsComponentLocked": false,
  "IsComponentTemplate": true,
  "IsCustomGroupControlTemplate": false,
  "IsPcfControl": false,
  "IsPremiumPcfControl": false,
  "IsWidgetTemplate": false,
  "LastModifiedTimestamp": "637876323127793341",
  "Name": "ee65712cedf944b38accbde33a5ae71c",
  "OverridableProperties": {},
  "Version": "637855760234820422"
}